llm_sorter/__init__.py
llm_sorter/llm_sorter.py
llm_sorter-0.1.0.dist-info/METADATA
llm_sorter-0.1.0.dist-info/WHEEL
llm_sorter-0.1.0.dist-info/licenses/LICENSE
llm_sorter-0.1.0.dist-info/RECORD
