Metadata-Version: 2.4
Name: llm-sorter
Version: 0.1.0
Summary: A Python library that uses LLMs as comparators for semantic sorting.
License-Expression: MIT
License-File: LICENSE
Author: Darshan Kalola
Author-email: darshanvkalola@gmail.com
Requires-Python: >=3.10,<4.0
Classifier: Programming Language :: Python :: 3
Classifier: Programming Language :: Python :: 3.10
Classifier: Programming Language :: Python :: 3.11
Classifier: Programming Language :: Python :: 3.12
Classifier: Programming Language :: Python :: 3.13
Classifier: Programming Language :: Python :: 3.14
Requires-Dist: pydantic-ai (>=1.37.0,<2.0.0)
Requires-Dist: pyright (>=1.1.0)
Requires-Dist: pytest (>=9.0.2,<10.0.0)
Requires-Dist: ruff (>=0.8.0)
Project-URL: Homepage, https://github.com/kalolad1/llm-sorter
Project-URL: Issues, https://github.com/kalolad1/llm-sorter/issues
